nonebot_plugin_alias/__init__.py
nonebot_plugin_alias-0.4.0.dist-info/LICENSE
nonebot_plugin_alias-0.4.0.dist-info/METADATA
nonebot_plugin_alias-0.4.0.dist-info/WHEEL
nonebot_plugin_alias-0.4.0.dist-info/RECORD
