Metadata-Version: 2.1
Name: nonebot_plugin_alias
Version: 0.4.0
Summary: A simple plugin for adding aliases for Nonebot command
Home-page: https://github.com/noneplugin/nonebot-plugin-alias
License: MIT
Author: meetwq
Author-email: meetwq@gmail.com
Requires-Python: >=3.9,<4.0
Classifier: License :: OSI Approved :: MIT License
Classifier: Programming Language :: Python :: 3
Classifier: Programming Language :: Python :: 3.9
Classifier: Programming Language :: Python :: 3.10
Classifier: Programming Language :: Python :: 3.11
Classifier: Programming Language :: Python :: 3.12
Requires-Dist: nonebot-plugin-alconna (>=0.51.4)
Requires-Dist: nonebot2 (>=2.3.0,<3.0.0)
Project-URL: Repository, https://github.com/noneplugin/nonebot-plugin-alias
